raugen/__init__.py
raugen-0.0.7.dist-info/LICENSE
raugen-0.0.7.dist-info/METADATA
raugen-0.0.7.dist-info/WHEEL
raugen-0.0.7.dist-info/top_level.txt
raugen-0.0.7.dist-info/RECORD
